corelab_blockkit/__init__.py
corelab_blockkit/blocks/__init__.py
corelab_blockkit/blocks/audio.py
corelab_blockkit/blocks/base.py
corelab_blockkit/blocks/download.py
corelab_blockkit/blocks/glossary.py
corelab_blockkit/blocks/image.py
corelab_blockkit/blocks/quote.py
corelab_blockkit/blocks/supplement.py
corelab_blockkit/blocks/text.py
corelab_blockkit/blocks/video.py
corelab_blockkit/enums.py
corelab_blockkit/exceptions.py
corelab_blockkit/list.py
corelab_blockkit/meta.py
corelab_blockkit/registry.py
corelab_blockkit/ser/__init__.py
corelab_blockkit/ser/json_codec.py
corelab_blockkit/ser/yaml_codec.py
corelab_blockkit-0.1.1.dist-info/LICENSE
corelab_blockkit-0.1.1.dist-info/METADATA
corelab_blockkit-0.1.1.dist-info/WHEEL
corelab_blockkit-0.1.1.dist-info/RECORD
