Metadata-Version: 2.3
Name: corelab-blockkit
Version: 0.1.1
Summary: A library for building and managing content blocks with standardized representation
License: Apache-2.0
Keywords: content,blocks,serialization,education,course
Author: CoreLab
Author-email: info@corelab.tech
Requires-Python: >=3.13
Classifier: Development Status :: 4 - Beta
Classifier: Intended Audience :: Developers
Classifier: License :: OSI Approved :: Apache Software License
Classifier: Programming Language :: Python :: 3
Classifier: Programming Language :: Python :: 3.13
Classifier: Topic :: Software Development :: Libraries
Classifier: Topic :: Education
Requires-Dist: pydantic (>=2.11.4,<3.0.0)
Requires-Dist: ruamel-yaml (>=0.18.10,<0.19.0)
Project-URL: Bug Tracker, https://github.com/CoreLab-Tech/BlockKit/issues
Project-URL: Homepage, https://github.com/CoreLab-Tech/BlockKit
